Workbook
Name Slicer_Category: #N/A
Name Slicer_Region: #N/A

Sheet Pivot_Analysis
A3: Region | B3: Revenue | C3: Profit | F3: Category & ProductName | G3: Revenue | H3: Profit | K3: Month | L3: Revenue | O3: SalesRep | P3: Revenue | T3: Category | U3: Revenue | V3: ProfitMargin
A4: East | B4: 28375270 | C4: 6115270 | F4: Accessories | G4: 4668515 | H4: 1450755 | K4: Jan | L4: 9674475 | O4: Priya Kumar | P4: 15612530 | T4: Accessories | U4: 4668515 | V4: 0.31075299
A5: West | B5: 23442750 | C5: 5172790 | F5: Headset | G5: 1909800 | H5: 607200 | K5: Feb | L5: 8877955 | O5: Neha Reddy | P5: 13848810 | T5: Electronics | U5: 87062300 | V5: 0.21564213
A6: South | B6: 21546420 | C6: 4814700 | F6: Webcam | G6: 1336800 | H6: 411680 | K6: Mar | L6: 6546505 | O6: Deepak Singh | P6: 12762740 | T6: Grand Total | U6: 91730815 | V6: 0.22048267
A7: North | B7: 18366375 | C7: 4122295 | F7: Keyboard | G7: 987390 | H7: 295590 | K7: Apr | L7: 5914695 | O7: Vikas Patel | P7: 11273110
A8: Grand Total | B8: 91730815 | C8: 20225055 | F8: Mouse | G8: 434525 | H8: 136285 | K8: May | L8: 8721095 | O8: Anita Verma | P8: 10724775
F9: Electronics | G9: 87062300 | H9: 18774300 | K9: Jun | L9: 8311075 | O9: Sunita Gupta | P9: 10273310
F10: Laptop | G10: 53757000 | H10: 11855000 | K10: Jul | L10: 8688405 | O10: Amit Shah | P10: 9593940
F11: Tablet | G11: 16485300 | H11: 3552300 | K11: Aug | L11: 7910720 | O11: Rahul Sharma | P11: 7641600
F12: Monitor | G12: 9831600 | H12: 2082600 | K12: Sep | L12: 7563525 | O12: Grand Total | P12: 91730815
F13: Printer | G13: 6988400 | H13: 1284400 | K13: Oct | L13: 7690455
F14: Grand Total | G14: 91730815 | H14: 20225055 | K14: Nov | L14: 6224620
K15: Dec | L15: 5607290
K16: Grand Total | L16: 91730815
B19: Sum of Revenue | C19: Sum of Profit | D19: Count of OrderID
B20: 91730815 | C20: 20225055 | D20: 987

Sheet Charts

Sheet Dashboard_Data
A1: Total Revenue | B1: =GETPIVOTDATA("Sum of Revenue",Pivot_Analysis!$B$19) -> 91730815
A2: Total Profit | B2: =GETPIVOTDATA("Sum of Profit",Pivot_Analysis!$B$19) -> 20225055
A3: Profit Margin | B3: =B2/B1 -> 0.22048267
A4: Total Orders | B4: =GETPIVOTDATA("Count of OrderID",Pivot_Analysis!$B$19) -> 987

Sheet Dashboard
B3: SALES PERFORMANCE DASHBOARD | 2025
B6: TOTAL REVENUE | F6: TOTAL PROFIT | J6: PROFIT MARGIN | N6: TOTAL ORDERS
B7: =Dashboard_Data!B1 -> 91730815 | F7: =Dashboard_Data!B2 -> 20225055 | J7: =Dashboard_Data!B3 -> 0.22048267 | N7: =Dashboard_Data!B4 -> 987
G33: Excludes 1 order with unknown product cost

Sheet Orders
A1: OrderID | B1: OrderDate | C1: Customer | D1: Region | E1: SalesRep | F1: ProductID | G1: Quantity | H1: UnitPrice | I1: Discount | J1: ProductName | K1: Category | L1: UnitCost | M1: Revenue | N1: Cost | O1: Profit | P1: Month
A2: ORD3001 | B2: 45889 | C2: Customer 013 | D2: West | E2: Amit Shah | F2: P108 | G2: 9 | H2: 1500 | I2: 0.1 | J2: =_xlfn.XLOOKUP(tblOrders[[#This Row],[ProductID]],Products!$A$2:$A$9,Products!$B$2:$B$9,"Unknown") -> Webcam | K2: =_xlfn.XLOOKUP(tblOrders[[#This Row],[ProductID]],Products!$A$2:$A$9,Products!$C$2:$C$9,"Unknown") -> Accessories | L2: =_xlfn.XLOOKUP(tblOrders[[#This Row],[ProductID]],Products!$A$2:$A$9,Products!$D$2:$D$9,0) -> 980 | M2: =tblOrders[[#This Row],[Quantity]]*tblOrders[[#This Row],[UnitPrice]]*(1-tblOrders[[#This Row],[Discount]]) -> 12150 | N2: =tblOrders[[#This Row],[Quantity]]*tblOrders[[#This Row],[UnitCost]] -> 8820 | O2: =tblOrders[[#This Row],[Revenue]]-tblOrders[[#This Row],[Cost]] -> 3330 | P2: =TEXT(tblOrders[[#This Row],[OrderDate]],"mmm") -> Aug
A3: ORD3002 | B3: 45920 | C3: Customer 020 | D3: West | E3: Amit Shah | F3: P103 | G3: 2 | H3: 12000 | I3: 0.05 | J3: =_xlfn.XLOOKUP(tblOrders[[#This Row],[ProductID]],Products!$A$2:$A$9,Products!$B$2:$B$9,"Unknown") -> Monitor | K3: =_xlfn.XLOOKUP(tblOrders[[#This Row],[ProductID]],Products!$A$2:$A$9,Products!$C$2:$C$9,"Unknown") -> Electronics | L3: =_xlfn.XLOOKUP(tblOrders[[#This Row],[ProductID]],Products!$A$2:$A$9,Products!$D$2:$D$9,0) -> 9000 | M3: =tblOrders[[#This Row],[Quantity]]*tblOrders[[#This Row],[UnitPrice]]*(1-tblOrders[[#This Row],[Discount]]) -> 22800 | N3: =tblOrders[[#This Row],[Quantity]]*tblOrders[[#This Row],[UnitCost]] -> 18000 | O3: =tblOrders[[#This Row],[Revenue]]-tblOrders[[#This Row],[Cost]] -> 4800 | P3: =TEXT(tblOrders[[#This Row],[OrderDate]],"mmm") -> Sep
A4: ORD3003 | B4: 45704 | C4: Customer 048 | D4: North | E4: Rahul Sharma | F4: P107 | G4: 8 | H4: 2000 | I4: 0.15 | J4: =_xlfn.XLOOKUP(tblOrders[[#This Row],[ProductID]],Products!$A$2:$A$9,Products!$B$2:$B$9,"Unknown") -> Headset | K4: =_xlfn.XLOOKUP(tblOrders[[#This Row],[ProductID]],Products!$A$2:$A$9,Products!$C$2:$C$9,"Unknown") -> Accessories | L4: =_xlfn.XLOOKUP(tblOrders[[#This Row],[ProductID]],Products!$A$2:$A$9,Products!$D$2:$D$9,0) -> 1300 | M4: =tblOrders[[#This Row],[Quantity]]*tblOrders[[#This Row],[UnitPrice]]*(1-tblOrders[[#This Row],[Discount]]) -> 13600 | N4: =tblOrders[[#This Row],[Quantity]]*tblOrders[[#This Row],[UnitCost]] -> 10400 | O4: =tblOrders[[#This Row],[Revenue]]-tblOrders[[#This Row],[Cost]] -> 3200 | P4: =TEXT(tblOrders[[#This Row],[OrderDate]],"mmm") -> Feb
A5: ORD3004 | B5: 45977 | C5: Customer 013 | D5: North | E5: Rahul Sharma | F5: P102 | G5: 1 | H5: 18000 | I5: 0 | J5: =_xlfn.XLOOKUP(tblOrders[[#This Row],[ProductID]],Products!$A$2:$A$9,Products!$B$2:$B$9,"Unknown") -> Tablet | K5: =_xlfn.XLOOKUP(tblOrders[[#This Row],[ProductID]],Products!$A$2:$A$9,Products!$C$2:$C$9,"Unknown") -> Electronics | L5: =_xlfn.XLOOKUP(tblOrders[[#This Row],[ProductID]],Products!$A$2:$A$9,Products!$D$2:$D$9,0) -> 13500 | M5: =tblOrders[[#This Row],[Quantity]]*tblOrders[[#This Row],[UnitPrice]]*(1-tblOrders[[#This Row],[Discount]]) -> 18000 | N5: =tblOrders[[#This Row],[Quantity]]*tblOrders[[#This Row],[UnitCost]] -> 13500 | O5: =tblOrders[[#This Row],[Revenue]]-tblOrders[[#This Row],[Cost]] -> 4500 | P5: =TEXT(tblOrders[[#This Row],[OrderDate]],"mmm") -> Nov
A6: ORD3005 | B6: 45965 | C6: Customer 038 | D6: North | E6: Rahul Sharma | F6: P108 | G6: 6 | H6: 1500 | I6: 0.05 | J6: =_xlfn.XLOOKUP(tblOrders[[#This Row],[ProductID]],Products!$A$2:$A$9,Products!$B$2:$B$9,"Unknown") -> Webcam | K6: =_xlfn.XLOOKUP(tblOrders[[#This Row],[ProductID]],Products!$A$2:$A$9,Products!$C$2:$C$9,"Unknown") -> Accessories | L6: =_xlfn.XLOOKUP(tblOrders[[#This Row],[ProductID]],Products!$A$2:$A$9,Products!$D$2:$D$9,0) -> 980 | M6: =tblOrders[[#This Row],[Quantity]]*tblOrders[[#This Row],[UnitPrice]]*(1-tblOrders[[#This Row],[Discount]]) -> 8550 | N6: =tblOrders[[#This Row],[Quantity]]*tblOrders[[#This Row],[UnitCost]] -> 5880 | O6: =tblOrders[[#This Row],[Revenue]]-tblOrders[[#This Row],[Cost]] -> 2670 | P6: =TEXT(tblOrders[[#This Row],[OrderDate]],"mmm") -> Nov
A7: ORD3006 | B7: 45923 | C7: Customer 043 | D7: South | E7: Vikas Patel | F7: P105 | G7: 8 | H7: 900 | I7: 0 | J7: =_xlfn.XLOOKUP(tblOrders[[#This Row],[ProductID]],Products!$A$2:$A$9,Products!$B$2:$B$9,"Unknown") -> Keyboard | K7: =_xlfn.XLOOKUP(tblOrders[[#This Row],[ProductID]],Products!$A$2:$A$9,Products!$C$2:$C$9,"Unknown") -> Accessories | L7: =_xlfn.XLOOKUP(tblOrders[[#This Row],[ProductID]],Products!$A$2:$A$9,Products!$D$2:$D$9,0) -> 600 | M7: =tblOrders[[#This Row],[Quantity]]*tblOrders[[#This Row],[UnitPrice]]*(1-tblOrders[[#This Row],[Discount]]) -> 7200 | N7: =tblOrders[[#This Row],[Quantity]]*tblOrders[[#This Row],[UnitCost]] -> 4800 | O7: =tblOrders[[#This Row],[Revenue]]-tblOrders[[#This Row],[Cost]] -> 2400 | P7: =TEXT(tblOrders[[#This Row],[OrderDate]],"mmm") -> Sep
A8: ORD3007 | B8: 45892 | C8: Customer 046 | D8: East | E8: Priya Kumar | F8: P107 | G8: 9 | H8: 2000 | I8: 0 | J8: =_xlfn.XLOOKUP(tblOrders[[#This Row],[ProductID]],Products!$A$2:$A$9,Products!$B$2:$B$9,"Unknown") -> Headset | K8: =_xlfn.XLOOKUP(tblOrders[[#This Row],[ProductID]],Products!$A$2:$A$9,Products!$C$2:$C$9,"Unknown") -> Accessories | L8: =_xlfn.XLOOKUP(tblOrders[[#This Row],[ProductID]],Products!$A$2:$A$9,Products!$D$2:$D$9,0) -> 1300 | M8: =tblOrders[[#This Row],[Quantity]]*tblOrders[[#This Row],[UnitPrice]]*(1-tblOrders[[#This Row],[Discount]]) -> 18000 | N8: =tblOrders[[#This Row],[Quantity]]*tblOrders[[#This Row],[UnitCost]] -> 11700 | O8: =tblOrders[[#This Row],[Revenue]]-tblOrders[[#This Row],[Cost]] -> 6300 | P8: =TEXT(tblOrders[[#This Row],[OrderDate]],"mmm") -> Aug
A9: ORD3008 | B9: 45819 | C9: Customer 037 | D9: South | E9: Vikas Patel | F9: P105 | G9: 1 | H9: 900 | I9: 0 | J9: =_xlfn.XLOOKUP(tblOrders[[#This Row],[ProductID]],Products!$A$2:$A$9,Products!$B$2:$B$9,"Unknown") -> Keyboard | K9: =_xlfn.XLOOKUP(tblOrders[[#This Row],[ProductID]],Products!$A$2:$A$9,Products!$C$2:$C$9,"Unknown") -> Accessories | L9: =_xlfn.XLOOKUP(tblOrders[[#This Row],[ProductID]],Products!$A$2:$A$9,Products!$D$2:$D$9,0) -> 600 | M9: =tblOrders[[#This Row],[Quantity]]*tblOrders[[#This Row],[UnitPrice]]*(1-tblOrders[[#This Row],[Discount]]) -> 900 | N9: =tblOrders[[#This Row],[Quantity]]*tblOrders[[#This Row],[UnitCost]] -> 600 | O9: =tblOrders[[#This Row],[Revenue]]-tblOrders[[#This Row],[Cost]] -> 300 | P9: =TEXT(tblOrders[[#This Row],[OrderDate]],"mmm") -> Jun
A10: ORD3009 | B10: 45863 | C10: Customer 002 | D10: North | E10: Rahul Sharma | F10: P105 | G10: 7 | H10: 900 | I10: 0 | J10: =_xlfn.XLOOKUP(tblOrders[[#This Row],[ProductID]],Products!$A$2:$A$9,Products!$B$2:$B$9,"Unknown") -> Keyboard | K10: =_xlfn.XLOOKUP(tblOrders[[#This Row],[ProductID]],Products!$A$2:$A$9,Products!$C$2:$C$9,"Unknown") -> Accessories | L10: =_xlfn.XLOOKUP(tblOrders[[#This Row],[ProductID]],Products!$A$2:$A$9,Products!$D$2:$D$9,0) -> 600 | M10: =tblOrders[[#This Row],[Quantity]]*tblOrders[[#This Row],[UnitPrice]]*(1-tblOrders[[#This Row],[Discount]]) -> 6300 | N10: =tblOrders[[#This Row],[Quantity]]*tblOrders[[#This Row],[UnitCost]] -> 4200 | O10: =tblOrders[[#This Row],[Revenue]]-tblOrders[[#This Row],[Cost]] -> 2100 | P10: =TEXT(tblOrders[[#This Row],[OrderDate]],"mmm") -> Jul
A11: ORD3010 | B11: 45767 | C11: Customer 046 | D11: South | E11: Sunita Gupta | F11: P101 | G11: 8 | H11: 55000 | I11: 0.05 | J11: =_xlfn.XLOOKUP(tblOrders[[#This Row],[ProductID]],Products!$A$2:$A$9,Products!$B$2:$B$9,"Unknown") -> Laptop | K11: =_xlfn.XLOOKUP(tblOrders[[#This Row],[ProductID]],Products!$A$2:$A$9,Products!$C$2:$C$9,"Unknown") -> Electronics | L11: =_xlfn.XLOOKUP(tblOrders[[#This Row],[ProductID]],Products!$A$2:$A$9,Products!$D$2:$D$9,0) -> 41000 | M11: =tblOrders[[#This Row],[Quantity]]*tblOrders[[#This Row],[UnitPrice]]*(1-tblOrders[[#This Row],[Discount]]) -> 418000 | N11: =tblOrders[[#This Row],[Quantity]]*tblOrders[[#This Row],[UnitCost]] -> 328000 | O11: =tblOrders[[#This Row],[Revenue]]-tblOrders[[#This Row],[Cost]] -> 90000 | P11: =TEXT(tblOrders[[#This Row],[OrderDate]],"mmm") -> Apr
A12: ORD3011 | B12: 45872 | C12: Customer 018 | D12: North | E12: Anita Verma | F12: P104 | G12: 13 | H12: 8000 | I12: 0.15 | J12: =_xlfn.XLOOKUP(tblOrders[[#This Row],[ProductID]],Products!$A$2:$A$9,Products!$B$2:$B$9,"Unknown") -> Printer | K12: =_xlfn.XLOOKUP(tblOrders[[#This Row],[ProductID]],Products!$A$2:$A$9,Products!$C$2:$C$9,"Unknown") -> Electronics | L12: =_xlfn.XLOOKUP(tblOrders[[#This Row],[ProductID]],Products!$A$2:$A$9,Products!$D$2:$D$9,0) -> 6200 | M12: =tblOrders[[#This Row],[Quantity]]*tblOrders[[#This Row],[UnitPrice]]*(1-tblOrders[[#This Row],[Discount]]) -> 88400 | N12: =tblOrders[[#This Row],[Quantity]]*tblOrders[[#This Row],[UnitCost]] -> 80600 | O12: =tblOrders[[#This Row],[Revenue]]-tblOrders[[#This Row],[Cost]] -> 7800 | P12: =TEXT(tblOrders[[#This Row],[OrderDate]],"mmm") -> Aug
A13: ORD3012 | B13: 45702 | C13: Customer 049 | D13: East | E13: Deepak Singh | F13: P106 | G13: 1 | H13: 500 | I13: 0.05 | J13: =_xlfn.XLOOKUP(tblOrders[[#This Row],[ProductID]],Products!$A$2:$A$9,Products!$B$2:$B$9,"Unknown") -> Mouse | K13: =_xlfn.XLOOKUP(tblOrders[[#This Row],[ProductID]],Products!$A$2:$A$9,Products!$C$2:$C$9,"Unknown") -> Accessories | L13: =_xlfn.XLOOKUP(tblOrders[[#This Row],[ProductID]],Products!$A$2:$A$9,Products!$D$2:$D$9,0) -> 320 | M13: =tblOrders[[#This Row],[Quantity]]*tblOrders[[#This Row],[UnitPrice]]*(1-tblOrders[[#This Row],[Discount]]) -> 475 | N13: =tblOrders[[#This Row],[Quantity]]*tblOrders[[#This Row],[UnitCost]] -> 320 | O13: =tblOrders[[#This Row],[Revenue]]-tblOrders[[#This Row],[Cost]] -> 155 | P13: =TEXT(tblOrders[[#This Row],[OrderDate]],"mmm") -> Feb
... A989: ORD4000 | B989: 45971 | C989: Customer 005 | D989: West | E989: Neha Reddy | F989: P105 | G989: 15 | H989: 900 | I989: 0 | J989: =_xlfn.XLOOKUP(tblOrders[[#This Row],[ProductID]],Products!$A$2:$A$9,Products!$B$2:$B$9,"Unknown") -> Keyboard | K989: =_xlfn.XLOOKUP(tblOrders[[#This Row],[ProductID]],Products!$A$2:$A$9,Products!$C$2:$C$9,"Unknown") -> Accessories | L989: =_xlfn.XLOOKUP(tblOrders[[#This Row],[ProductID]],Products!$A$2:$A$9,Products!$D$2:$D$9,0) -> 600 | M989: =tblOrders[[#This Row],[Quantity]]*tblOrders[[#This Row],[UnitPrice]]*(1-tblOrders[[#This Row],[Discount]]) -> 13500 | N989: =tblOrders[[#This Row],[Quantity]]*tblOrders[[#This Row],[UnitCost]] -> 9000 | O989: =tblOrders[[#This Row],[Revenue]]-tblOrders[[#This Row],[Cost]] -> 4500 | P989: =TEXT(tblOrders[[#This Row],[OrderDate]],"mmm") -> Nov
A990: Total | M990: =SUBTOTAL(109,tblOrders[Revenue]) -> 92126815 | N990: =SUBTOTAL(109,tblOrders[Cost]) -> 71505760 | O990: =SUBTOTAL(109,tblOrders[Profit]) -> 20621055

Sheet Products
A1: ProductID | B1: Product | C1: Category | D1: UnitCost
A2: P101 | B2: Laptop | C2: Electronics | D2: 41000 | E2: =COUNTIF(Orders!$F$2:$F$989,Products!A2) -> 137
A3: P102 | B3: Tablet | C3: Electronics | D3: 13500 | E3: =COUNTIF(Orders!$F$2:$F$989,Products!A3) -> 121
A4: P103 | B4: Monitor | C4: Electronics | D4: 9000 | E4: =COUNTIF(Orders!$F$2:$F$989,Products!A4) -> 108
A5: P104 | B5: Printer | C5: Electronics | D5: 6200 | E5: =COUNTIF(Orders!$F$2:$F$989,Products!A5) -> 115
A6: P105 | B6: Keyboard | C6: Accessories | D6: 600 | E6: =COUNTIF(Orders!$F$2:$F$989,Products!A6) -> 134
A7: P106 | B7: Mouse | C7: Accessories | D7: 320 | E7: =COUNTIF(Orders!$F$2:$F$989,Products!A7) -> 126
A8: P107 | B8: Headset | C8: Accessories | D8: 1300 | E8: =COUNTIF(Orders!$F$2:$F$989,Products!A8) -> 125
A9: P108 | B9: Webcam | C9: Accessories | D9: 980 | E9: =COUNTIF(Orders!$F$2:$F$989,Products!A9) -> 121
E11: =SUM(E2:E9) -> 987
E13: =COUNTA(Orders!E2:E989) -> 988

Sheet Targets
A1: Month | B1: RevenueTarget
A2: 45658 | B2: 1860000
A3: 45689 | B3: 1920000
A4: 45717 | B4: 1980000
A5: 45748 | B5: 2040000
A6: 45778 | B6: 2100000
A7: 45809 | B7: 2160000
A8: 45839 | B8: 2220000
A9: 45870 | B9: 2280000
A10: 45901 | B10: 2340000
A11: 45931 | B11: 2400000
A12: 45962 | B12: 2460000
A13: 45992 | B13: 2520000

Sheet Cleaning_Log
A1: Column | B1: Problem | C1: Rows affected | D1: Fix | E1: check
A2: Customer | B2: some cells are blank | C2: 9 | D2: put unknown | E2: TRUE
A3: Region | B3: Some Region values are written in different cases, like ‘north’ and ‘NORTH’. | C3: 14 | D3: Use PROPER to standardize the case | E3: TRUE
A4: Region | B4: some values have extra spaces before or after the word | C4: 12 | D4: Use TRIM to remove the spaces | E4: TRUE
A5: Quantity | B5: some cells are blank | C5: 12 | D5: Deleted the 12 rows with blank Quantity, because Revenue cannot be calculated without it. | E5: TRUE
A6: OrderID | B6: Some OrderID values are duplicated | C6: 15 | D6: remove duplicate rows | E6: TRUE
A7: ProductID | B7: ProductID P199 does not exist in the Products sheet. | C7: 1 | D7: Keep it and mark ProductID as Unknown | E7: TRUE
A8: UnitCost | B8: ProductID P199 has no cost in the Products sheet, so UnitCost is set to 0. | C8: 1 | D8: Confirm the product with the client. Until then, Profit for this order is overstated.
